python_playvox/__init__.py
python_playvox/errors.py
python_playvox/helpers.py
python_playvox-0.2.1.dist-info/WHEEL
python_playvox-0.2.1.dist-info/METADATA
python_playvox-0.2.1.dist-info/RECORD
