Metadata-Version: 2.1
Name: python-playvox
Version: 0.2.1
Summary: A Python wrapper for the Playvox REST API.
Home-page: https://git.moseswynn.com/moseswynn/python-playvox
Keywords: playvox,API,wrapper
Author: Moses Wynn
Author-email: mail@moseswynn.com
Requires-Python: >=3.6,<4.0
Classifier: Programming Language :: Python :: 3
Classifier: Programming Language :: Python :: 3.6
Classifier: Programming Language :: Python :: 3.7
Classifier: Programming Language :: Python :: 3.8
Requires-Dist: requests (>=2.23.0,<3.0.0)
